turbo_c2/__init__.py
turbo_c2/abstractions/__init__.py
turbo_c2/abstractions/job_group.py
turbo_c2/abstractions/job_group_with_instances.py
turbo_c2/abstractions/job_parameter.py
turbo_c2/abstractions/pipeline.py
turbo_c2/abstractions/pipeline_node.py
turbo_c2/api/__init__.py
turbo_c2/api/controller/__init__.py
turbo_c2/api/controller/job_controller.py
turbo_c2/api/domain/__init__.py
turbo_c2/api/domain/dto/__init__.py
turbo_c2/api/domain/dto/job/__init__.py
turbo_c2/api/domain/dto/job/create_job_group_request.py
turbo_c2/api/domain/dto/job/job_instance_data_request.py
turbo_c2/api/domain/dto/job/position_definition_request.py
turbo_c2/api/domain/dto/job/scale_job_request.py
turbo_c2/api/helpers.py
turbo_c2/api/service/__init__.py
turbo_c2/api/service/job_service.py
turbo_c2/api/service/metrics_service.py
turbo_c2/central_api/__init__.py
turbo_c2/central_api/central_api_api.py
turbo_c2/central_api/default_central_api.py
turbo_c2/central_api/local_central_api.py
turbo_c2/central_api/remote_central_api.py
turbo_c2/clients/__init__.py
turbo_c2/clients/prometheus/__init__.py
turbo_c2/clients/prometheus/prometheus_http_client.py
turbo_c2/clients/prometheus/prometheus_metrics_client.py
turbo_c2/clients/prometheus/remote_prometheus_metrics_api.py
turbo_c2/commands.py
turbo_c2/decorators/__init__.py
turbo_c2/decorators/actor.py
turbo_c2/decorators/config.py
turbo_c2/decorators/controller.py
turbo_c2/decorators/extra_api.py
turbo_c2/decorators/job.py
turbo_c2/decorators/job_creator.py
turbo_c2/decorators/job_definition.py
turbo_c2/decorators/node.py
turbo_c2/decorators/pipeline.py
turbo_c2/decorators/queue.py
turbo_c2/decorators/queue_creator.py
turbo_c2/domain/__init__.py
turbo_c2/domain/gui/decision_layout_element.py
turbo_c2/domain/gui/elements_definition.py
turbo_c2/domain/gui/external_job_group_definition.py
turbo_c2/domain/gui/layout_definition.py
turbo_c2/domain/gui/layout_element.py
turbo_c2/domain/gui/layout_element_command.py
turbo_c2-0.0.1a3.dist-info/METADATA
turbo_c2-0.0.1a3.dist-info/WHEEL
turbo_c2-0.0.1a3.dist-info/RECORD
